Workbook
Name Slicer_Category: #N/A
Name Slicer_City: #N/A
Name Slicer_Payment_Mode: #N/A
Name Slicer_Product: #N/A
Name Slicer_Region: #N/A
Name Slicer_Sales: #N/A

Sheet Sheet1
A1: Date | B1: Invoice No | C1: Customer Name | D1: Customer Segment | E1: State | F1: City | G1: Region | H1: Product | I1: Category | J1: Quantity | K1: Unit Price | L1: Discount % | M1: Sales | N1: Cost | O1: Profit | P1: Payment Mode | Q1: Delivery Status | R1: Salesperson | S1: Year | T1: Month
A2: 07-12-2025 | B2: INV000001 | C2: Prime Sales | D2: Retail | E2: Gujarat | F2: Surat | G2: South | H2: Laptop | I2: Electronics | J2: 25 | K2: 45000 | L2: 8 | M2: 1035000 | N2: 836283.47 | O2: 198716.53 | P2: Net Banking | Q2: Pending | R2: Raj | S2: =YEAR(A2) -> 2025 | T2: =MONTH(A2) -> 12
A3: 02-10-2025 | B3: INV000002 | C3: Vision Mart | D3: Retail | E3: Delhi | F3: New Delhi | G3: East | H3: Laptop | I3: Electronics | J3: 15 | K3: 45000 | L3: 3 | M3: 654750 | N3: 558982.45 | O3: 95767.55 | P3: Debit Card | Q3: Pending | R3: Vikas | S3: =YEAR(A3) -> 2025 | T3: =MONTH(A3) -> 10
A4: 23-05-2025 | B4: INV000003 | C4: Shree Enterprises | D4: Corporate | E4: Karnataka | F4: Mysuru | G4: North | H4: Laptop | I4: Electronics | J4: 11 | K4: 45000 | L4: 12 | M4: 435600 | N4: 347128.24 | O4: 88471.76 | P4: Net Banking | Q4: In Transit | R4: Raj | S4: =YEAR(A4) -> 2025 | T4: =MONTH(A4) -> 5
A5: 24-09-2025 | B5: INV000004 | C5: Vision Mart | D5: Wholesale | E5: Maharashtra | F5: Nagpur | G5: East | H5: Router | I5: Networking | J5: 9 | K5: 2500 | L5: 2 | M5: 22050 | N5: 19410.65 | O5: 2639.35 | P5: Net Banking | Q5: Delivered | R5: Raj | S5: =YEAR(A5) -> 2025 | T5: =MONTH(A5) -> 9
A6: 18-09-2025 | B6: INV000005 | C6: Tech World | D6: Retail | E6: Gujarat | F6: Surat | G6: East | H6: SSD | I6: Storage | J6: 19 | K6: 4500 | L6: 0 | M6: 85500 | N6: 70607.68 | O6: 14892.32 | P6: Net Banking | Q6: Pending | R6: Karan | S6: =YEAR(A6) -> 2025 | T6: =MONTH(A6) -> 9
A7: 18-05-2025 | B7: INV000006 | C7: Sai Mart | D7: Wholesale | E7: Delhi | F7: New Delhi | G7: South | H7: Router | I7: Networking | J7: 1 | K7: 2500 | L7: 8 | M7: 2300 | N7: 2052.08 | O7: 247.92 | P7: UPI | Q7: In Transit | R7: Karan | S7: =YEAR(A7) -> 2025 | T7: =MONTH(A7) -> 5
A8: 23-06-2025 | B8: INV000007 | C8: Metro Retail | D8: Retail | E8: Gujarat | F8: Vadodara | G8: South | H8: Mouse | I8: Accessories | J8: 18 | K8: 600 | L8: 0 | M8: 10800 | N8: 8944.65 | O8: 1855.35 | P8: Cash | Q8: Delivered | R8: Priya | S8: =YEAR(A8) -> 2025 | T8: =MONTH(A8) -> 6
A9: 28-05-2025 | B9: INV000008 | C9: Ganesh Stores | D9: Wholesale | E9: Maharashtra | F9: Mumbai | G9: South | H9: Router | I9: Networking | J9: 6 | K9: 2500 | L9: 4 | M9: 14400 | N9: 11570.72 | O9: 2829.28 | P9: Cash | Q9: Delivered | R9: Raj | S9: =YEAR(A9) -> 2025 | T9: =MONTH(A9) -> 5
A10: 10-04-2025 | B10: INV000009 | C10: Metro Retail | D10: Corporate | E10: Maharashtra | F10: Mumbai | G10: South | H10: Printer | I10: Electronics | J10: 25 | K10: 12000 | L10: 1 | M10: 297000 | N10: 251911.99 | O10: 45088.01 | P10: Cash | Q10: In Transit | R10: Pooja | S10: =YEAR(A10) -> 2025 | T10: =MONTH(A10) -> 4
A11: 26-12-2025 | B11: INV000010 | C11: Rahul Traders | D11: Corporate | E11: Gujarat | F11: Vadodara | G11: West | H11: SSD | I11: Storage | J11: 11 | K11: 4500 | L11: 15 | M11: 42075 | N11: 39162.44 | O11: 2912.56 | P11: UPI | Q11: Delivered | R11: Sneha | S11: =YEAR(A11) -> 2025 | T11: =MONTH(A11) -> 12
A12: 03-07-2025 | B12: INV000011 | C12: Metro Retail | D12: Retail | E12: Karnataka | F12: Bengaluru | G12: East | H12: Router | I12: Networking | J12: 13 | K12: 2500 | L12: 7 | M12: 30225 | N12: 22772.36 | O12: 7452.64 | P12: Cash | Q12: Returned | R12: Karan | S12: =YEAR(A12) -> 2025 | T12: =MONTH(A12) -> 7
A13: 04-08-2025 | B13: INV000012 | C13: Ganesh Stores | D13: Wholesale | E13: Gujarat | F13: Surat | G13: East | H13: Printer | I13: Electronics | J13: 24 | K13: 12000 | L13: 16 | M13: 241920 | N13: 218541.7 | O13: 23378.3 | P13: Credit Card | Q13: Pending | R13: Karan | S13: =YEAR(A13) -> 2025 | T13: =MONTH(A13) -> 8
... A4999: 14-03-2025 | B4999: INV004998 | C4999: Shree Enterprises | D4999: Wholesale | E4999: Karnataka | F4999: Bengaluru | G4999: North | H4999: Laptop | I4999: Electronics | J4999: 8 | K4999: 45000 | L4999: 11 | M4999: 320400 | N4999: 243604.81 | O4999: 76795.19 | P4999: Net Banking | Q4999: Pending | R4999: Sneha | S4999: =YEAR(A4999) -> 2025 | T4999: =MONTH(A4999) -> 3
A5000: 45564 | B5000: INV004999 | C5000: Ganesh Stores | D5000: Retail | E5000: Gujarat | F5000: Vadodara | G5000: East | H5000: Printer | I5000: Electronics | J5000: 18 | K5000: 12000 | L5000: 17 | M5000: 179280 | N5000: 130083.27 | O5000: 49196.73 | P5000: Credit Card | Q5000: In Transit | R5000: Priya | S5000: =YEAR(A5000) -> 2024 | T5000: =MONTH(A5000) -> 9
A5001: 45565 | B5001: INV005000 | C5001: Vision Mart | D5001: Corporate | E5001: Gujarat | F5001: Ahmedabad | G5001: East | H5001: UPS | I5001: Electronics | J5001: 17 | K5001: 3500 | L5001: 11 | M5001: 52955 | N5001: 43391.73 | O5001: 9563.27 | P5001: UPI | Q5001: Returned | R5001: Priya | S5001: =YEAR(A5001) -> 2024 | T5001: =MONTH(A5001) -> 9
A5002: 45566 | B5002: INV005001 | C5002: Shree Enterprises | D5002: Retail | E5002: Gujarat | F5002: Vadodara | G5002: South | H5002: Keyboard | I5002: Accessories | J5002: 9 | K5002: 900 | L5002: 15 | M5002: 6885 | N5002: 5946.91 | O5002: 938.09 | P5002: Credit Card | Q5002: Pending | R5002: Raj | S5002: =YEAR(A5002) -> 2024 | T5002: =MONTH(A5002) -> 10
A5003: 45567 | B5003: INV005002 | C5003: Bright Solutions | D5003: Retail | E5003: Gujarat | F5003: Ahmedabad | G5003: South | H5003: UPS | I5003: Electronics | J5003: 11 | K5003: 3500 | L5003: 13 | M5003: 33495 | N5003: 24550.56 | O5003: 8944.44 | P5003: UPI | Q5003: In Transit | R5003: Sneha | S5003: =YEAR(A5003) -> 2024 | T5003: =MONTH(A5003) -> 10
A5004: 45568 | B5004: INV005003 | C5004: Shree Enterprises | D5004: Retail | E5004: Maharashtra | F5004: Pune | G5004: South | H5004: SSD | I5004: Storage | J5004: 22 | K5004: 4500 | L5004: 9 | M5004: 90090 | N5004: 76584.87 | O5004: 13505.13 | P5004: Cash | Q5004: In Transit | R5004: Vikas | S5004: =YEAR(A5004) -> 2024 | T5004: =MONTH(A5004) -> 10
A5005: 45569 | B5005: INV005004 | C5005: Ganesh Stores | D5005: Retail | E5005: Gujarat | F5005: Surat | G5005: East | H5005: SSD | I5005: Storage | J5005: 11 | K5005: 4500 | L5005: 2 | M5005: 48510 | N5005: 43640.02 | O5005: 4869.98 | P5005: Debit Card | Q5005: Pending | R5005: Pooja | S5005: =YEAR(A5005) -> 2024 | T5005: =MONTH(A5005) -> 10
A5006: 45570 | B5006: INV005005 | C5006: Prime Sales | D5006: Corporate | E5006: Gujarat | F5006: Vadodara | G5006: South | H5006: Printer | I5006: Electronics | J5006: 23 | K5006: 12000 | L5006: 2 | M5006: 270480 | N5006: 227190.41 | O5006: 43289.59 | P5006: UPI | Q5006: Pending | R5006: Karan | S5006: =YEAR(A5006) -> 2024 | T5006: =MONTH(A5006) -> 10
A5007: 45571 | B5007: INV005006 | C5007: Shree Enterprises | D5007: Retail | E5007: Karnataka | F5007: Mysuru | G5007: West | H5007: Mouse | I5007: Accessories | J5007: 4 | K5007: 600 | L5007: 1 | M5007: 2376 | N5007: 1855.19 | O5007: 520.81 | P5007: Net Banking | Q5007: Pending | R5007: Pooja | S5007: =YEAR(A5007) -> 2024 | T5007: =MONTH(A5007) -> 10
A5008: 45572 | B5008: INV005007 | C5008: Om Retail | D5008: Corporate | E5008: Karnataka | F5008: Bengaluru | G5008: North | H5008: Mouse | I5008: Accessories | J5008: 19 | K5008: 600 | L5008: 4 | M5008: 10944 | N5008: 8683.1 | O5008: 2260.9 | P5008: UPI | Q5008: Pending | R5008: Sneha | S5008: =YEAR(A5008) -> 2024 | T5008: =MONTH(A5008) -> 10
A5009: 45573 | B5009: INV005008 | C5009: Om Retail | D5009: Corporate | E5009: Maharashtra | F5009: Pune | G5009: South | H5009: Laptop | I5009: Electronics | J5009: 16 | K5009: 45000 | L5009: 6 | M5009: 676800 | N5009: 604561.56 | O5009: 72238.44 | P5009: Credit Card | Q5009: Returned | R5009: Pooja | S5009: =YEAR(A5009) -> 2024 | T5009: =MONTH(A5009) -> 10
A5010: 45574 | B5010: INV005009 | C5010: Vision Mart | D5010: Wholesale | E5010: Gujarat | F5010: Ahmedabad | G5010: West | H5010: Router | I5010: Networking | J5010: 6 | K5010: 2500 | L5010: 18 | M5010: 12300 | N5010: 10390.35 | O5010: 1909.65 | P5010: Debit Card | Q5010: Delivered | R5010: Raj | S5010: =YEAR(A5010) -> 2024 | T5010: =MONTH(A5010) -> 10
A5011: 45575 | B5011: INV005010 | C5011: Smart Retail | D5011: Corporate | E5011: Delhi | F5011: New Delhi | G5011: South | H5011: Mouse | I5011: Accessories | J5011: 4 | K5011: 600 | L5011: 9 | M5011: 2184 | N5011: 1799.25 | O5011: 384.75 | P5011: Cash | Q5011: Delivered | R5011: Raj | S5011: =YEAR(A5011) -> 2024 | T5011: =MONTH(A5011) -> 10
... A10001: 45441 | B10001: INV010000 | C10001: Tech World | D10001: Wholesale | E10001: Delhi | F10001: New Delhi | G10001: East | H10001: Printer | I10001: Electronics | J10001: 12 | K10001: 12000 | L10001: 5 | M10001: 136800 | N10001: 99205.87 | O10001: 37594.13 | P10001: UPI | Q10001: Returned | R10001: Sneha | S10001: =YEAR(A10001) -> 2024 | T10001: =MONTH(A10001) -> 5

Sheet pivot table 
A3: Region | B3: Count of City | D3: State | E3: Sum of Profit | G3: Payment Mode | H3: Count of Customer Segment | J3: Sum of Sales | K3: Sum of Profit | L3: Sum of Quantity | M3: Count of Product
A4: East | B4: 2194 | D4: Delhi | E4: 48255901 | G4: Cash | H4: 1692 | J4: 1170979828 | K4: 1.9800806e+08 | L4: 113511 | M4: 8762
A5: North | B5: 2200 | D5: Gujarat | E5: 51289087 | G5: Credit Card | H5: 1727
A6: South | B6: 2145 | D6: Karnataka | E6: 46634800 | G6: Debit Card | H6: 1792
A7: West | B7: 2223 | D7: Maharashtra | E7: 51828274 | G7: Net Banking | H7: 1813 | J7: #VALUE!
A8: Grand Total | B8: 8762 | D8: Grand Total | E8: 1.9800806e+08 | G8: UPI | H8: 1738
G9: Grand Total | H9: 8762
A12: Category | B12: Count of City | D12: Product | E12: Sum of Profit | G12: City | H12: Sum of Sales
A13: Accessories | B13: 2523 | D13: Keyboard | E13: 2286190.7 | G13: Ahmedabad | H13: 11886
A14: Electronics | B14: 4976 | D14: Laptop | E14: 1.1601682e+08 | G14: Bengaluru | H14: 13572
A15: Networking | B15: 1263 | D15: Monitor | E15: 34396514 | G15: Mumbai | H15: 13212
A16: Grand Total | B16: 8762 | D16: Mouse | E16: 1462925.2 | G16: Mysuru | H16: 15216 | J16: Row Labels | K16: Count of Delivery Status
D17: Printer | E17: 28763797 | G17: Nagpur | H17: 984 | J17: Delivered | K17: 2188
D18: Router | E18: 6323724.1 | G18: Nashik | H18: 6492 | J18: In Transit | K18: 2143
D19: UPS | E19: 8758093.6 | G19: New Delhi | H19: 25818 | J19: Pending | K19: 2202
D20: Grand Total | E20: 1.9800806e+08 | G20: Pune | H20: 2208 | J20: Returned | K20: 2229
G21: Surat | H21: 8856 | J21: Grand Total | K21: 8762
G22: Vadodara | H22: 12996
G23: Grand Total | H23: 111240

Sheet KPIs
D9: sum of sales | E9: =GETPIVOTDATA("Sum of Sales",'pivot table '!$J$3) -> 1170979828 | G9: Delivered | H9: =GETPIVOTDATA("Delivery Status",'pivot table '!$J$16,"Delivery Status","Delivered") -> 2188
D10: sum of profit | E10: =GETPIVOTDATA("Sum of Profit",'pivot table '!$J$3) -> 1.9800806e+08 | G10: In Transit | H10: =GETPIVOTDATA("Delivery Status",'pivot table '!$J$16,"Delivery Status","In Transit") -> 2143
D11: sum of quantity | E11: =GETPIVOTDATA("Sum of Quantity",'pivot table '!$J$3) -> 113511 | G11: Pending | H11: =GETPIVOTDATA("Delivery Status",'pivot table '!$J$16,"Delivery Status","Pending") -> 2202
D12: count of products | E12: =GETPIVOTDATA("Count of Product",'pivot table '!$J$3) -> 8762 | G12: Returned | H12: =GETPIVOTDATA("Delivery Status",'pivot table '!$J$16,"Delivery Status","Returned") -> 2229
D13: profit margin | E13: =E10/E9 -> 0.16909605

Sheet dashboard
C1: SALES & PROFIT DASHBOARD
C8: PROFIT BY PRODUCT | H8: ORDERS BY REGION | M8: ORDERS BY CATEGORY
C18: ORDERS BY PAYMENT MODE | H18: PROFIT BY STATE | M18: SALES BY CITY
C28: DELIVERY STATUS
